<?xml version="1.0" encoding="UTF-8"?>
<objects serializationModel="Studio.01.10.00">
    <object class="AudioFile" id="{8086e5bf-5d1b-4553-a2d9-5da8fd2c1c2c}">
        <property name="assetPath">
            <value>Steps_Twig_03.wav</value>
        </property>
        <property name="frequencyInKHz">
            <value>48</value>
        </property>
        <property name="channelCount">
            <value>2</value>
        </property>
        <property name="length">
            <value>0.67733333333333334</value>
        </property>
        <relationship name="masterAssetFolder">
            <destination>{bbf96001-6200-4665-8cb6-c770563e075f}</destination>
        </relationship>
    </object>
</objects>
